cache_money/__init__.py
cache_money/cache.py
cache_money/constants.py
cache_money/engine.py
cache_money/utils.py
cache_money-1.3.0.dist-info/LICENSE
cache_money-1.3.0.dist-info/METADATA
cache_money-1.3.0.dist-info/WHEEL
cache_money-1.3.0.dist-info/RECORD
