Metadata-Version: 2.1
Name: cache-money
Version: 1.3.0
Summary: Async cache decorator for memoization using aioredis.
Home-page: https://github.com/novisto/cache-money
License: MIT
Keywords: redis,cache,async
Author: Alexandre Jutras
Author-email: alexandre.jutras@novisto.com
Maintainer: Alexandre Jutras
Maintainer-email: alexandre.jutras@novisto.com
Requires-Python: >=3.8.1,<3.13
Classifier: Development Status :: 5 - Production/Stable
Classifier: License :: OSI Approved :: MIT License
Classifier: Programming Language :: Python :: 3
Classifier: Programming Language :: Python :: 3.9
Classifier: Programming Language :: Python :: 3.10
Classifier: Programming Language :: Python :: 3.11
Classifier: Programming Language :: Python :: 3.12
Classifier: Programming Language :: Python :: 3.8
Requires-Dist: redis (>=4.5.1,<5.0.0)
Project-URL: Repository, https://github.com/novisto/cache-money
